{
  "slug": "agua-negra",
  "name": "Paso Agua Negra",
  "schedule": null,
  "scheduleRaw": "Todos los días de la semana, incluidos feriados.",
  "rawStatus": "CERRADO",
  "statusDetail": "CERRADO",
  "scheduleText": null,
  "scheduleDays": "Todos los días de la semana, incluidos feriados.",
  "motivo": null,
  "motivoInfo": null,
  "htmlAlerts": [
    "Días de apertura: Todos los días de la semana, incluidos feriados.",
    "Vehículos hasta 22 butacas",
    "Velocidad moderada"
  ],
  "vialidadRuta": "150",
  "vialidadTramo": "Arrequintin - Lte. Con Chile",
  "vialidadEstado": "CORTE TOTAL",
  "vialidadObservaciones": "Transitable",
  "restriccionPasajeros": "Vehículos hasta 22 butacas",
  "restriccionVelocidad": "moderada",
  "latestTweet": null,
  "weather": {
    "temperatureC": 4,
    "description": "Soleado",
    "wind": "SSW a 9 km/h",
    "visibilityKm": 10,
    "sunrise": "08:30",
    "sunset": "18:57",
    "updatedAt": "2026-07-20",
    "feelsLikeC": 2,
    "humidity": 72
  },
  "contact": null,
  "lat": -30.32783,
  "lng": -69.23614,
  "altitudeM": 4780,
  "scrapedAt": "2026-07-20T16:45:55.387Z",
  "forecast": [
    {
      "period": "Hoy por la tarde",
      "description": "Lluvia localizada en las cercanías",
      "temperatureC": 7,
      "wind": "SW 9 km/h",
      "visibility": "Buena"
    },
    {
      "period": "Hoy por la noche",
      "description": "Parcialmente nublado",
      "temperatureC": 4,
      "wind": "WSW 10 km/h",
      "visibility": "Buena"
    },
    {
      "period": "Mañana por la mañana",
      "description": "Aguacero con nieve ligera",
      "temperatureC": 1,
      "wind": "WNW 4 km/h",
      "visibility": "Buena"
    },
    {
      "period": "Mañana al mediodía",
      "description": "Aguacero con nieve ligera",
      "temperatureC": 2,
      "wind": "E 4 km/h",
      "visibility": "Buena"
    }
  ],
  "sources": {
    "status": "aguanegra.sanjuan.gob.ar",
    "clima": "https://wttr.in",
    "statusUpdatedAt": "10 de junio de 2026 • 10:37 hs"
  },
  "lastKnownGoodAt": "2026-07-20T16:45:55.387Z"
}
